LICENSE
MANIFEST.in
README.rst
setup.py
il2fb/parsers/game_log/__init__.py
il2fb/parsers/game_log/constants.py
il2fb/parsers/game_log/events.py
il2fb/parsers/game_log/l10n.py
il2fb/parsers/game_log/parsers.py
il2fb/parsers/game_log/priority.py
il2fb/parsers/game_log/regex.py
il2fb/parsers/game_log/transformers.py
il2fb/parsers/game_log/locale/en/LC_MESSAGES/il2fb-game-log-parser.mo
il2fb/parsers/game_log/locale/en/LC_MESSAGES/il2fb-game-log-parser.po
il2fb/parsers/game_log/locale/ru/LC_MESSAGES/il2fb-game-log-parser.mo
il2fb/parsers/game_log/locale/ru/LC_MESSAGES/il2fb-game-log-parser.po
il2fb_game_log_parser.egg-info/PKG-INFO
il2fb_game_log_parser.egg-info/SOURCES.txt
il2fb_game_log_parser.egg-info/dependency_links.txt
il2fb_game_log_parser.egg-info/namespace_packages.txt
il2fb_game_log_parser.egg-info/requires.txt
il2fb_game_log_parser.egg-info/top_level.txt
requirements/dist.txt